pyflutterinstall/__init__.py
pyflutterinstall/cli.py
pyflutterinstall/config.py
pyflutterinstall/flutter_doctor.py
pyflutterinstall/interactive_execute.py
pyflutterinstall/paths.py
pyflutterinstall/postrun.py
pyflutterinstall/print_env.py
pyflutterinstall/resources.py
pyflutterinstall/setenv.py
pyflutterinstall/util.py
pyflutterinstall/which_all.py
pyflutterinstall/archive/trampoline.py
pyflutterinstall/install/__init__.py
pyflutterinstall/install/android_sdk.py
pyflutterinstall/install/ant_sdk.py
pyflutterinstall/install/chrome.py
pyflutterinstall/install/flutter_sdk.py
pyflutterinstall/install/gradle.py
pyflutterinstall/install/java_sdk.py
pyflutterinstall/install/win/msys-2.0.dll
pyflutterinstall/install/win/msys-iconv-2.dll
pyflutterinstall/install/win/msys-intl-8.dll
pyflutterinstall/install/win/yes.exe
pyflutterinstall-1.5.0.dist-info/LICENSE
pyflutterinstall-1.5.0.dist-info/METADATA
pyflutterinstall-1.5.0.dist-info/WHEEL
pyflutterinstall-1.5.0.dist-info/entry_points.txt
pyflutterinstall-1.5.0.dist-info/top_level.txt
pyflutterinstall-1.5.0.dist-info/RECORD
