Metadata-Version: 2.1
Name: pyflutterinstall
Version: 1.5.0
Summary: Installs Android studio and everything using the flutter doctor command.
Home-page: https://github.com/zackees/pyflutterinstall
License: BSD 3-Clause License
Keywords: android,install,flutter,android sdk
Classifier: Programming Language :: Python :: 3
Requires-Python: >=3.9
License-File: LICENSE
Requires-Dist: download
Requires-Dist: colorama
Requires-Dist: setenvironment >=2.0.3
Requires-Dist: appdirs >=1.4.4
Requires-Dist: requests
Provides-Extra: test
Requires-Dist: pytest ; extra == 'test'
Requires-Dist: pytest-cov ; extra == 'test'
